geolidar/__init__.py
geolidar/script.py
scripts/__init__.py
scripts/script.py
geolidar-0.0.3.dist-info/METADATA
geolidar-0.0.3.dist-info/WHEEL
geolidar-0.0.3.dist-info/top_level.txt
geolidar-0.0.3.dist-info/RECORD
